LICENSE.txt
MANIFEST.in
README.md
setup.cfg
setup.py
udacity/__init__.py
udacity/catalog.py
udacity/user.py
udacity.egg-info/PKG-INFO
udacity.egg-info/SOURCES.txt
udacity.egg-info/dependency_links.txt
udacity.egg-info/requires.txt
udacity.egg-info/top_level.txt