Metadata-Version: 1.1
Name: udacity
Version: 1.0.0
Summary: Library for interacting with Udacity account data and course progress
Home-page: https://github.com/tylucaskelley/udacity-api-python
Author: Ty-Lucas Kelley
Author-email: tylucaskelley@gmail.com
License: MIT
Download-URL: https://github.com/tylucaskelley/udacity-api-python/tarball/v1.0.0
Keywords: education,api,udacity,courses,mooc
Platform: UNKNOWN
Classifier: Programming Language :: Python
Classifier: Operating System :: MacOS :: MacOS X
Classifier: Operating System :: POSIX :: Linux
Classifier: License :: OSI Approved :: MIT License
Classifier: Intended Audience :: Developers
Classifier: Topic :: Software Development :: Libraries :: Python Modules
Classifier: Topic :: Utilities
Classifier: Topic :: Internet :: WWW/HTTP
